{"ongoing_trials": {}, "hyperparameters": {"space": [{"class_name": "Int", "config": {"name": "lstm1_units", "default": null, "conditions": [], "min_value": 16, "max_value": 128, "step": 16, "sampling": "linear"}}, {"class_name": "Float", "config": {"name": "dropout1", "default": 0.1, "conditions": [], "min_value": 0.1, "max_value": 0.5, "step": 0.1, "sampling": "linear"}}, {"class_name": "Int", "config": {"name": "lstm2_units", "default": null, "conditions": [], "min_value": 8, "max_value": 64, "step": 8, "sampling": "linear"}}, {"class_name": "Float", "config": {"name": "dropout2", "default": 0.1, "conditions": [], "min_value": 0.1, "max_value": 0.5, "step": 0.1, "sampling": "linear"}}], "values": {"lstm1_units": 16, "dropout1": 0.1, "lstm2_units": 8, "dropout2": 0.1}}, "start_order": ["00", "01", "02", "03", "04", "05", "06", "07", "08", "09"], "end_order": ["00", "01", "02", "03", "04", "05", "06", "07", "08", "09"], "run_times": {"00": 1, "01": 1, "02": 1, "03": 1, "04": 1, "05": 1, "06": 1, "07": 1, "08": 1, "09": 1}, "retry_queue": [], "seed": 7199, "seed_state": 7239, "tried_so_far": ["756a5299c195c0c1882534b90db63f13", "f4a6c23dbf17d5a060565568d782fa2e", "c5367846a2a21a324654345b863225dd", "3d96094f6a17b4609bb6d3cba08a5f41", "7d277e44eccce1735038215a7de909e1", "36c276c714cd6f24926f7a63ebb6853d", "f532a2a05f5308e25fbb2584d921ffbc", "5e6a4de585be3ea078c15f0efe4d3f8b", "2b4e7a87f4eaa46d541e405363cd20f8", "9ade46b3c28064b378a4a1cfe41b9ba7"], "id_to_hash": {"00": "3d96094f6a17b4609bb6d3cba08a5f41", "01": "5e6a4de585be3ea078c15f0efe4d3f8b", "02": "f532a2a05f5308e25fbb2584d921ffbc", "03": "f4a6c23dbf17d5a060565568d782fa2e", "04": "36c276c714cd6f24926f7a63ebb6853d", "05": "c5367846a2a21a324654345b863225dd", "06": "756a5299c195c0c1882534b90db63f13", "07": "9ade46b3c28064b378a4a1cfe41b9ba7", "08": "2b4e7a87f4eaa46d541e405363cd20f8", "09": "7d277e44eccce1735038215a7de909e1"}, "display": {"search_start": "2025-06-16T11:21:42.010963", "trial_start": {"00": "2025-06-16T11:21:42.010963", "01": "2025-06-16T11:27:47.005155", "02": "2025-06-16T11:30:21.440969", "03": "2025-06-16T11:33:04.632447", "04": "2025-06-16T11:36:56.826385", "05": "2025-06-16T11:40:34.128702", "06": "2025-06-16T11:44:30.870614", "07": "2025-06-16T11:52:34.981187", "08": "2025-06-16T11:56:03.961568", "09": "2025-06-16T12:00:24.240473"}, "trial_number": {"00": 1, "01": 2, "02": 3, "03": 4, "04": 5, "05": 6, "06": 7, "07": 8, "08": 9, "09": 10}}}